gamr_backend_api_service/__init__.py
gamr_backend_api_service/__main__.py
gamr_backend_api_service/settings.py
gamr_backend_api_service/api/__init__.py
gamr_backend_api_service/api/factory.py
gamr_backend_api_service/api/routes/__init__.py
gamr_backend_api_service/api/routes/base.py
gamr_backend_api_service/api/routes/exception_handlers.py
gamr_backend_api_service/api/routes/flower.py
gamr_backend_api_service/api/routes/object.py
gamr_backend_api_service/auth/__init__.py
gamr_backend_api_service/auth/exceptions.py
gamr_backend_api_service/auth/token_generator.py
gamr_backend_api_service/database_connector/__init__.py
gamr_backend_api_service/database_connector/abstract_database_connector.py
gamr_backend_api_service/database_connector/firebase.py
gamr_backend_api_service/ml_service_client/__init__.py
gamr_backend_api_service/ml_service_client/abstract_ml_service_client.py
gamr_backend_api_service/ml_service_client/hugging_face/__init__.py
gamr_backend_api_service/ml_service_client/hugging_face/errors.py
gamr_backend_api_service/ml_service_client/hugging_face/hf_client.py
gamr_backend_api_service/ml_service_client/mlflow/__init__.py
gamr_backend_api_service/ml_service_client/mlflow/errors.py
gamr_backend_api_service/ml_service_client/mlflow/mlflow_client.py
gamr_backend_api_service/models/__init__.py
gamr_backend_api_service/models/abstract_payload.py
gamr_backend_api_service/models/user.py
gamr_backend_api_service/models/hugging_face/__init__.py
gamr_backend_api_service/models/hugging_face/payload.py
gamr_backend_api_service/models/mlflow/__init__.py
gamr_backend_api_service/models/mlflow/dataset.py
gamr_backend_api_service/models/mlflow/flower_payload.py
gamr_backend_api_service/models/mlflow/models.py
gamr_backend_api_service/models/mlflow/versions.py
gamr_backend_api_service/services/__init__.py
gamr_backend_api_service/services/user_manager.py
tests/__init__.py
tests/api/__init__.py
tests/api/test_api.py
tests/api/routes/__init__.py
tests/api/routes/base.py
gamr_backend_api_service-1.0.14.dist-info/METADATA
gamr_backend_api_service-1.0.14.dist-info/WHEEL
gamr_backend_api_service-1.0.14.dist-info/top_level.txt
gamr_backend_api_service-1.0.14.dist-info/RECORD
