Metadata-Version: 2.2
Name: gamr_backend_api_service
Version: 1.0.14
Requires-Dist: fastapi==0.115.0
Requires-Dist: uvicorn==0.34.0
Requires-Dist: numpy==1.26.4
Requires-Dist: gradio-client==1.5.0
Requires-Dist: python-multipart==0.0.18
Requires-Dist: pyjwt==2.10.1
Requires-Dist: firebase-admin==6.6.0
Requires-Dist: pydantic_settings
Dynamic: description
Dynamic: description-content-type
Dynamic: requires-dist
